reactor_sdk/__init__.py
reactor_sdk/interface.py
reactor_sdk/py.typed
reactor_sdk/reactor.py
reactor_sdk/types.py
reactor_sdk/coordinator/__init__.py
reactor_sdk/coordinator/client.py
reactor_sdk/coordinator/local_client.py
reactor_sdk/model/__init__.py
reactor_sdk/model/client.py
reactor_sdk/utils/__init__.py
reactor_sdk/utils/tokens.py
reactor_sdk/utils/webrtc.py
reactor_sdk-0.1.0.dist-info/METADATA
reactor_sdk-0.1.0.dist-info/WHEEL
reactor_sdk-0.1.0.dist-info/licenses/LICENSE
reactor_sdk-0.1.0.dist-info/RECORD
