Metadata-Version: 2.4
Name: reactor-sdk
Version: 0.1.0
Summary: Python SDK for Reactor - Real-time AI video streaming
Project-URL: Homepage, https://reactor.inc
Project-URL: Documentation, https://docs.reactor.inc
Project-URL: Repository, https://github.com/reactor-team/py-sdk
Author-email: Reactor Technologies <support@reactor.inc>
License-File: LICENSE
Classifier: Development Status :: 3 - Alpha
Classifier: Intended Audience :: Developers
Classifier: License :: OSI Approved :: MIT License
Classifier: Programming Language :: Python :: 3
Classifier: Programming Language :: Python :: 3.10
Classifier: Programming Language :: Python :: 3.11
Classifier: Programming Language :: Python :: 3.12
Classifier: Topic :: Multimedia :: Video
Classifier: Topic :: Scientific/Engineering :: Artificial Intelligence
Requires-Python: >=3.10
Requires-Dist: aiohttp>=3.9.0
Requires-Dist: aiortc>=1.9.0
Requires-Dist: av>=12.0.0
Requires-Dist: numpy>=1.24.0
Provides-Extra: dev
Requires-Dist: mypy>=1.8.0; extra == 'dev'
Requires-Dist: pytest-asyncio>=0.23.0; extra == 'dev'
Requires-Dist: pytest>=8.0.0; extra == 'dev'
Requires-Dist: ruff>=0.3.0; extra == 'dev'
